{"_type":"export","__export_format":4,"__export_date":"2019-10-13T16:09:06.604Z","__export_source":"insomnia.desktop.app:v7.0.1","resources":[{"_id":"req_c8f2e386d4c94de9b92aeb3a01fcfaac","authentication":{},"body":{},"created":1570979868269,"description":"","headers":[],"isPrivate":false,"metaSortKey":-1570979868269,"method":"GET","modified":1570981948821,"name":"Orders of person","parameters":[],"parentId":"fld_edc5d400764c48a9aaa67703f4b6f969","settingDisableRenderRequestBody":false,"settingEncodeUrl":true,"settingRebuildPath":true,"settingSendCookies":true,"settingStoreCookies":true,"url":"{{ base_url  }}/people/1/orders","_type":"request"},{"_id":"fld_edc5d400764c48a9aaa67703f4b6f969","created":1570979817079,"description":"","environment":{},"environmentPropertyOrder":null,"metaSortKey":-1570979821881,"modified":1570979824340,"name":"People","parentId":"fld_2d39434f5c794720ae6ded9f575c820e","_type":"request_group"},{"_id":"fld_2d39434f5c794720ae6ded9f575c820e","created":1570979809015,"description":"","environment":{},"environmentPropertyOrder":null,"metaSortKey":-1570979809015,"modified":1570979809015,"name":"Challenge","parentId":"wrk_ef4d5b4416534b91abb52e8c42aecfa5","_type":"request_group"},{"_id":"wrk_ef4d5b4416534b91abb52e8c42aecfa5","created":1570977484812,"description":"","modified":1570977484812,"name":"Insomnia","parentId":null,"_type":"workspace"},{"_id":"req_61ce956e039c4ef79ac73ecf0c4dc83a","authentication":{},"body":{},"created":1570979859932,"description":"","headers":[],"isPrivate":false,"metaSortKey":-1570979859932,"method":"GET","modified":1570980150795,"name":"Phones of person","parameters":[],"parentId":"fld_edc5d400764c48a9aaa67703f4b6f969","settingDisableRenderRequestBody":false,"settingEncodeUrl":true,"settingRebuildPath":true,"settingSendCookies":true,"settingStoreCookies":true,"url":"{{ base_url  }}/people/1/phones","_type":"request"},{"_id":"req_5d8fec07f734420a9a8a378bfc0f7949","authentication":{},"body":{},"created":1570979846700,"description":"","headers":[],"isPrivate":false,"metaSortKey":-1570979846700,"method":"GET","modified":1570979921827,"name":"List Person","parameters":[],"parentId":"fld_edc5d400764c48a9aaa67703f4b6f969","settingDisableRenderRequestBody":false,"settingEncodeUrl":true,"settingRebuildPath":true,"settingSendCookies":true,"settingStoreCookies":true,"url":"{{ base_url  }}/people/1","_type":"request"},{"_id":"req_94f54a358d4746c7a8e4b5c06c0f092b","authentication":{},"body":{},"created":1570979837764,"description":"","headers":[],"isPrivate":false,"metaSortKey":-1570979837765,"method":"GET","modified":1570979899568,"name":"List People","parameters":[],"parentId":"fld_edc5d400764c48a9aaa67703f4b6f969","settingDisableRenderRequestBody":false,"settingEncodeUrl":true,"settingRebuildPath":true,"settingSendCookies":true,"settingStoreCookies":true,"url":"{{ base_url  }}/people","_type":"request"},{"_id":"req_7ff39640cff14a13bb6feb3446fdaa72","authentication":{},"body":{},"created":1570982783279,"description":"","headers":[],"isPrivate":false,"metaSortKey":-1570982783279,"method":"GET","modified":1570982784999,"name":"List Items","parameters":[],"parentId":"fld_72859e47424244959651adc81605965d","settingDisableRenderRequestBody":false,"settingEncodeUrl":true,"settingRebuildPath":true,"settingSendCookies":true,"settingStoreCookies":true,"url":"{{ base_url  }}/orders/3/items","_type":"request"},{"_id":"fld_72859e47424244959651adc81605965d","created":1570979821831,"description":"","environment":{},"environmentPropertyOrder":null,"metaSortKey":-1570979821831,"modified":1570979821831,"name":"Orders","parentId":"fld_2d39434f5c794720ae6ded9f575c820e","_type":"request_group"},{"_id":"req_82947f18092f4f0aa5a06a35e9a84980","authentication":{},"body":{},"created":1570982765922,"description":"","headers":[],"isPrivate":false,"metaSortKey":-1570982765922,"method":"GET","modified":1570982773543,"name":"List Ship","parameters":[],"parentId":"fld_72859e47424244959651adc81605965d","settingDisableRenderRequestBody":false,"settingEncodeUrl":true,"settingRebuildPath":true,"settingSendCookies":true,"settingStoreCookies":true,"url":"{{ base_url  }}/orders/1/ship","_type":"request"},{"_id":"req_7c1e538d34054498951e78a5c6a560b1","authentication":{},"body":{},"created":1570982745519,"description":"","headers":[],"isPrivate":false,"metaSortKey":-1570982745519,"method":"GET","modified":1570982753101,"name":"List Orders","parameters":[],"parentId":"fld_72859e47424244959651adc81605965d","settingDisableRenderRequestBody":false,"settingEncodeUrl":true,"settingRebuildPath":true,"settingSendCookies":true,"settingStoreCookies":true,"url":"{{ base_url  }}/orders","_type":"request"},{"_id":"req_fec848d9fe88482c83f8f8e2c3add02c","authentication":{},"body":{},"created":1570982155834,"description":"","headers":[],"isPrivate":false,"metaSortKey":-1570982155834,"method":"GET","modified":1570982791017,"name":"List Order","parameters":[],"parentId":"fld_72859e47424244959651adc81605965d","settingDisableRenderRequestBody":false,"settingEncodeUrl":true,"settingRebuildPath":true,"settingSendCookies":true,"settingStoreCookies":true,"url":"{{ base_url  }}/orders/3","_type":"request"},{"_id":"env_0aa9a0a7b0837dfbdd9ba503b8ebeae827c7adb5","color":null,"created":1570977484911,"data":{"base_url":"http://localhost:8000/api"},"dataPropertyOrder":{"&":["base_url"]},"isPrivate":false,"metaSortKey":1570977484911,"modified":1570979889205,"name":"Base Environment","parentId":"wrk_ef4d5b4416534b91abb52e8c42aecfa5","_type":"environment"},{"_id":"jar_0aa9a0a7b0837dfbdd9ba503b8ebeae827c7adb5","cookies":[],"created":1570977484931,"modified":1570977484931,"name":"Default Jar","parentId":"wrk_ef4d5b4416534b91abb52e8c42aecfa5","_type":"cookie_jar"}]}